.source                  HOME.java
.class                   public HOME
.super                   java/lang/Object
.method public <init>()V
    .limit stack 32
    .limit locals 1
    aload_0
    invokespecial java/lang/Object/<init>()V
return
.end method

.method public Setup()V
    .limit stack 32
    .limit locals 1
.line 2
    aload_0
    invokevirtual HOME/hejz()Ljava/util/ArrayList;
    pop
.line 3
    aload_0
    invokevirtual HOME/hejx()Ljava/util/ArrayList;
    pop
    getstatic java/lang/System/out Ljava/io/PrintStream;
    ldc "Great Success!!"
    invokevirtual java/io/PrintStream.println(Ljava/lang/String;)V
    return
.end method

.method public static main([Ljava/lang/String;)V
    .limit stack 32
    .limit locals 1
    new HOME
    dup
    invokespecial HOME/<init>()V
    invokespecial HOME/Setup()V
    return
.end method

.method public hejz()Ljava/util/ArrayList;
    .limit stack 11
    .limit locals 3
.line 9
    new java/util/ArrayList
    dup
    invokespecial java/util/ArrayList.<init>()V
    astore 1
    new java/util/ArrayList
    dup
    invokespecial java/util/ArrayList.<init>()V
    astore 2
    aload 2
    ldc "lol2"
    invokeinterface java/util/List.add(Ljava/lang/Object;)Z 2
    pop
    aload 1
    aload 2
    invokeinterface java/util/List.add(Ljava/lang/Object;)Z 2
    pop
.line 10
    aload 1
    areturn
.end method

.method public hejx()Ljava/util/ArrayList;
    .limit stack 11
    .limit locals 3
.line 16
    new java/util/ArrayList
    dup
    invokespecial java/util/ArrayList.<init>()V
    astore 1
    new java/util/ArrayList
    dup
    invokespecial java/util/ArrayList.<init>()V
    astore 2
    aload 2
    ldc "lol2"
    invokeinterface java/util/List.add(Ljava/lang/Object;)Z 2
    pop
    aload 1
    aload 2
    invokeinterface java/util/List.add(Ljava/lang/Object;)Z 2
    pop
    areturn
.end method

