
    getstatic java/lang/System/out Ljava/io/PrintStream;
    dload_1
    invokevirtual java/io/PrintStream/println(D)V

    getstatic java/lang/System/out Ljava/io/PrintStream;
    iload_1
    invokevirtual java/io/PrintStream/println(I)V


    getstatic java/lang/System/out Ljava/io/PrintStream;
    iload_1
    invokevirtual java/io/PrintStream/println(Z)V



    iload 4
    invokevirtual java/io/PrintStream.println(I)V

    iload_1
    iconst_1
    ifeq Label19
    getstatic java/lang/System/out Ljava/io/PrintStream;
    ldc "false"
    invokevirtual java/io/PrintStream/println(Ljava/lang/String;)V
    goto Label20
    Label19:
    getstatic java/lang/System/out Ljava/io/PrintStream;
    ldc "true"
    invokevirtual java/io/PrintStream/println(Ljava/lang/String;)V
    Label20:



    getstatic java/lang/System/out Ljava/io/PrintStream;
